Workbook
Name Slicer_Account_Name: #N/A

Sheet Chart of Accounts
A1: Accounts | C1: Accounts | D1: Sub Accounts | E1: Financial Statement | F1: Indivdual Accounts | G1: Sub Accounts
A2: Assets | C2: Assets | D2: Current Assets | E2: Balance Sheet | F2: Cash | G2: Current Assets
A3: Liabilities | C3: Assets | D3: Fixed Accounts | E3: Balance Sheet | F3: Owner's Equity | G3: Equity
A4: Equity | C4: Assets | D4: Contra Assets | E4: Balance Sheet | F4: Office Furniture | G4: Fixed Assets
A5: Expenses | C5: Liabilities | D5: Current Liabilities | E5: Balance Sheet | F5: Accounts Payable | G5: Current Liabilities
A6: Revenue | C6: Liabilities | D6: Fixed Liabilities | E6: Balance Sheet | F6: Payroll Payable | G6: Current Liabilities
C7: Equity | D7: Equity | E7: Income Statement | F7: Service Revenue | G7: Current Assets
C8: Expenses | D8: Expenses | E8: Income Statement | F8: Accounts Recieveable | G8: Current Assets
C9: Revenue | D9: Revenue | E9: Income Statement | F9: Office Supplies | G9: Current Assets
F10: Rent Expense | G10: Expenses
F11: Utility Expense | G11: Expenses
F12: Payroll | G12: Expenses
F13: Depreciation Expense | G13: Expenses
F14: Accumlated Expenses | G14: Contra Assets
F15: Taxes
F16: Govt
F17: N/A

Sheet Journal Entry
D2: Swift Tech Solutions
A3: January
A4: T.No | B4: Date | C4: Account Name | D4: Account Number | E4: Description | F4: Debit | G4: Credit | H4: Running Balance
A5: 1 | B5: 45658 | C5: Owner's Equity | D5: 201 | E5: Owner Investment | G5: 10000 | H5: =IF(C5="Cash",SUMIF(C$5:C5,"Cash",F$5:F5)-SUMIF(C$5:C5,"Cash",G$5:G5),"")
A6: 1 | B6: 45658 | C6: Cash | D6: 101 | E6: Owner Investment | F6: 10000 | H6: =IF(C6="Cash",SUMIF(C$5:C6,"Cash",F$5:F6)-SUMIF(C$5:C6,"Cash",G$5:G6),"") -> 10000
A7: 2 | B7: 45660 | C7: Office Furniture | D7: 301 | E7: Purchase of office funiture on credit | F7: 2500 | H7: =IF(C7="Cash",SUMIF(C$5:C7,"Cash",F$5:F7)-SUMIF(C$5:C7,"Cash",G$5:G7),"")
A8: 2 | B8: 45660 | C8: Accounts Payable | D8: 401 | E8: Purchase of office furniture on credit | G8: 2500 | H8: =IF(C8="Cash",SUMIF(C$5:C8,"Cash",F$5:F8)-SUMIF(C$5:C8,"Cash",G$5:G8),"")
A9: 3 | B9: 45662 | C9: Service Revenue | D9: 601 | E9: IT Consulting Service on account: Client 1 | G9: 4000 | H9: =IF(C9="Cash",SUMIF(C$5:C9,"Cash",F$5:F9)-SUMIF(C$5:C9,"Cash",G$5:G9),"")
A10: 3 | B10: 45662 | C10: Accounts Recieveable | D10: 501 | E10: IT Consulting Service on account: Client 1 | F10: 4000 | H10: =IF(C10="Cash",SUMIF(C$5:C10,"Cash",F$5:F10)-SUMIF(C$5:C10,"Cash",G$5:G10),"")
A11: 4 | B11: 45665 | C11: Office Supplies | D11: 701 | E11: Purchase of office supplies | F11: 600 | H11: =IF(C11="Cash",SUMIF(C$5:C11,"Cash",F$5:F11)-SUMIF(C$5:C11,"Cash",G$5:G11),"")
A12: 4 | B12: 45665 | C12: Cash | D12: 101 | E12: Purchase of office supplies | G12: 600 | H12: =IF(C12="Cash",SUMIF(C$5:C12,"Cash",F$5:F12)-SUMIF(C$5:C12,"Cash",G$5:G12),"") -> 9400
A13: 5 | B13: 45667 | C13: Cash | D13: 101 | E13: Cash from account client 1 | F13: 2000 | H13: =IF(C13="Cash",SUMIF(C$5:C13,"Cash",F$5:F13)-SUMIF(C$5:C13,"Cash",G$5:G13),"") -> 11400
A14: 5 | B14: 45667 | C14: Accounts Recieveable | D14: 501 | E14: Cash from account client 1 | G14: 2000 | H14: =IF(C14="Cash",SUMIF(C$5:C14,"Cash",F$5:F14)-SUMIF(C$5:C14,"Cash",G$5:G14),"")
A15: 6 | B15: 45672 | C15: Cash | D15: 101 | E15: Office furniture purchased on credit | G15: 2500 | H15: =IF(C15="Cash",SUMIF(C$5:C15,"Cash",F$5:F15)-SUMIF(C$5:C15,"Cash",G$5:G15),"") -> 8900
A16: 6 | B16: 45672 | C16: Accounts Payable | D16: 401 | E16: Office furniture purchased on credit | F16: 2500 | H16: =IF(C16="Cash",SUMIF(C$5:C16,"Cash",F$5:F16)-SUMIF(C$5:C16,"Cash",G$5:G16),"")
A17: 7 | B17: 45677 | C17: Service Revenue | D17: 601 | E17: IT Consulting Service, Unpaid | G17: 3000 | H17: =IF(C17="Cash",SUMIF(C$5:C17,"Cash",F$5:F17)-SUMIF(C$5:C17,"Cash",G$5:G17),"")
A18: 7 | B18: 45677 | C18: Accounts Recieveable | D18: 501 | E18: IT Consulting Service, Unpaid | F18: 3000 | H18: =IF(C18="Cash",SUMIF(C$5:C18,"Cash",F$5:F18)-SUMIF(C$5:C18,"Cash",G$5:G18),"")
A19: 8 | B19: 45682 | C19: Rent Expense | D19: 901 | E19: Rent for the month | F19: 1200 | H19: =IF(C19="Cash",SUMIF(C$5:C19,"Cash",F$5:F19)-SUMIF(C$5:C19,"Cash",G$5:G19),"")
A20: 8 | B20: 45682 | C20: Cash | D20: 101 | E20: Rent for the month | G20: 1200 | H20: =IF(C20="Cash",SUMIF(C$5:C20,"Cash",F$5:F20)-SUMIF(C$5:C20,"Cash",G$5:G20),"") -> 7700
A21: 9 | B21: 45685 | C21: Utility Expense | D21: 702 | E21: Utility bill for the month, Unpaid | F21: 500 | H21: =IF(C21="Cash",SUMIF(C$5:C21,"Cash",F$5:F21)-SUMIF(C$5:C21,"Cash",G$5:G21),"")
A22: 9 | B22: 45685 | C22: Accounts Payable | D22: 401 | E22: Utility bill for the month, Unpaid | G22: 500 | H22: =IF(C22="Cash",SUMIF(C$5:C22,"Cash",F$5:F22)-SUMIF(C$5:C22,"Cash",G$5:G22),"")
A23: 10 | B23: 45688 | C23: Payroll | D23: 801 | E23: Pays employee salaries | F23: 3000 | H23: =IF(C23="Cash",SUMIF(C$5:C23,"Cash",F$5:F23)-SUMIF(C$5:C23,"Cash",G$5:G23),"")
A24: 10 | B24: 45688 | C24: Cash | D24: 101 | E24: Pays employee salaries | G24: 3000 | H24: =IF(C24="Cash",SUMIF(C$5:C24,"Cash",F$5:F24)-SUMIF(C$5:C24,"Cash",G$5:G24),"") -> 4700
A25: 11 | B25: 45688 | C25: Depreciation Expense | D25: 301 | E25: Adjusted entry- Depreciation Expense on Office Furniture | F25: 100 | H25: =IF(C25="Cash",SUMIF(C$5:C25,"Cash",F$5:F25)-SUMIF(C$5:C25,"Cash",G$5:G25),"")
A26: 11 | B26: 45688 | C26: Accumlated Expenses | D26: 802 | E26: Adjusted entry- Depreciation Expense on Office Furniture | G26: 100 | H26: =IF(C26="Cash",SUMIF(C$5:C26,"Cash",F$5:F26)-SUMIF(C$5:C26,"Cash",G$5:G26),"")
A27: 12 | B27: 45688 | C27: Payroll | D27: 801 | E27: Adjusted Entry- Accured Wages, Unpaid | F27: 1500 | H27: =IF(C27="Cash",SUMIF(C$5:C27,"Cash",F$5:F27)-SUMIF(C$5:C27,"Cash",G$5:G27),"")
A28: 12 | B28: 45688 | C28: Payroll Payable | D28: 402 | E28: Adjusted Entry- Accured Wages, Unpaid | G28: 1500 | H28: =IF(C28="Cash",SUMIF(C$5:C28,"Cash",F$5:F28)-SUMIF(C$5:C28,"Cash",G$5:G28),"")
A29: 13 | B29: 45688 | C29: Taxes | D29: 803 | E29: Payable Taxes to Govt | F29: 58
A30: 13 | B30: 45688 | C30: Govt | D30: 804 | E30: Payable Taxes to Govt | G30: 58
E31: Total | F31: =SUM(F5:F30)-SUM(G5:G30) -> 0
F32: =SUM(F5:F30) -> 30958 | G32: =SUM(G5:G30) -> 30958

Sheet Ledger
A2: =B4 -> Cash | C2: =VLOOKUP(A2,'Chart of Accounts'!F:G,2,0) -> Current Assets
A3: Date | B3: Account Name | C3: Description | D3: T.No | E3: Sum of Debit | F3: Sum of Credit | G3: Sum of Balance
A4: 45658 | B4: Cash | C4: Owner Investment | D4: 1 | E4: 10000 | G4: 10000
A5: 45658 | B5: Owner's Equity | C5: Owner Investment | D5: 1 | F5: 10000 | G5: -10000
A6: 45660 | B6: Accounts Payable | C6: Purchase of office furniture on credit | D6: 2 | F6: 2500 | G6: -2500
A7: 45660 | B7: Office Furniture | C7: Purchase of office funiture on credit | D7: 2 | E7: 2500 | G7: 2500
A8: 45662 | B8: Accounts Recieveable | C8: IT Consulting Service on account: Client 1 | D8: 3 | E8: 4000 | G8: 4000
A9: 45662 | B9: Service Revenue | C9: IT Consulting Service on account: Client 1 | D9: 3 | F9: 4000 | G9: -4000
A10: 45665 | B10: Cash | C10: Purchase of office supplies | D10: 4 | F10: 600 | G10: -600
A11: 45665 | B11: Office Supplies | C11: Purchase of office supplies | D11: 4 | E11: 600 | G11: 600
A12: 45667 | B12: Accounts Recieveable | C12: Cash from account client 1 | D12: 5 | F12: 2000 | G12: -2000
A13: 45667 | B13: Cash | C13: Cash from account client 1 | D13: 5 | E13: 2000 | G13: 2000
A14: 45672 | B14: Accounts Payable | C14: Office furniture purchased on credit | D14: 6 | E14: 2500 | G14: 2500
A15: 45672 | B15: Cash | C15: Office furniture purchased on credit | D15: 6 | F15: 2500 | G15: -2500
A16: 45677 | B16: Accounts Recieveable | C16: IT Consulting Service, Unpaid | D16: 7 | E16: 3000 | G16: 3000
A17: 45677 | B17: Service Revenue | C17: IT Consulting Service, Unpaid | D17: 7 | F17: 3000 | G17: -3000
A18: 45682 | B18: Cash | C18: Rent for the month | D18: 8 | F18: 1200 | G18: -1200
A19: 45682 | B19: Rent Expense | C19: Rent for the month | D19: 8 | E19: 1200 | G19: 1200
A20: 45685 | B20: Accounts Payable | C20: Utility bill for the month, Unpaid | D20: 9 | F20: 500 | G20: -500
A21: 45685 | B21: Utility Expense | C21: Utility bill for the month, Unpaid | D21: 9 | E21: 500 | G21: 500
A22: 45688 | B22: Cash | C22: Pays employee salaries | D22: 10 | F22: 3000 | G22: -3000
A23: 45688 | B23: Depreciation Expense | C23: Adjusted entry- Depreciation Expense on Office Furniture | D23: 11 | E23: 100 | G23: 100
A24: 45688 | B24: Accumlated Expenses | C24: Adjusted entry- Depreciation Expense on Office Furniture | D24: 11 | F24: 100 | G24: -100
A25: 45688 | B25: Payroll | C25: Adjusted Entry- Accured Wages, Unpaid | D25: 12 | E25: 1500 | G25: 1500
A26: 45688 | B26: Payroll | C26: Pays employee salaries | D26: 10 | E26: 3000 | G26: 3000
A27: 45688 | B27: Payroll Payable | C27: Adjusted Entry- Accured Wages, Unpaid | D27: 12 | F27: 1500 | G27: -1500
A28: 45688 | B28: Taxes | C28: Payable Taxes to Govt | D28: 13 | E28: 58 | G28: 58
A29: 45688 | B29: Govt | C29: Payable Taxes to Govt | D29: 13 | F29: 58 | G29: -58
A30: Grand Total | E30: 30958 | F30: 30958 | G30: 0

Sheet Trial Balance
A2: Trial Balance
A3: Account Name | B3: Sum of Debit | C3: Sum of Credit | D3: Sum of Balance
A4: Accounts Payable | B4: 2500 | C4: 3000 | D4: -500 | F4: =VLOOKUP($A4,'Chart of Accounts'!F:G,2,0) -> Current Liabilities | G4: =VLOOKUP(F4,'Chart of Accounts'!$C:$E,3,0) -> #N/A
A5: Accounts Recieveable | B5: 7000 | C5: 2000 | D5: 5000 | F5: =VLOOKUP($A5,'Chart of Accounts'!F:G,2,0) -> Current Assets | G5: =VLOOKUP(F5,'Chart of Accounts'!$C:$E,3,0) -> #N/A
A6: Cash | B6: 12000 | C6: 7300 | D6: 4700 | F6: =VLOOKUP($A6,'Chart of Accounts'!F:G,2,0) -> Current Assets | G6: =VLOOKUP(F6,'Chart of Accounts'!$C:$E,3,0) -> #N/A
A7: Office Furniture | B7: 2500 | D7: 2500 | F7: =VLOOKUP($A7,'Chart of Accounts'!F:G,2,0) -> Fixed Assets | G7: =VLOOKUP(F7,'Chart of Accounts'!$C:$E,3,0) -> #N/A
A8: Office Supplies | B8: 600 | D8: 600 | F8: =VLOOKUP($A8,'Chart of Accounts'!F:G,2,0) -> Current Assets | G8: =VLOOKUP(F8,'Chart of Accounts'!$C:$E,3,0) -> #N/A
A9: Owner's Equity | C9: 10000 | D9: -10000 | F9: =VLOOKUP($A9,'Chart of Accounts'!F:G,2,0) -> Equity | G9: =VLOOKUP(F9,'Chart of Accounts'!$C:$E,3,0) -> Income Statement
A10: Rent Expense | B10: 1200 | D10: 1200 | F10: =VLOOKUP($A10,'Chart of Accounts'!F:G,2,0) -> Expenses | G10: =VLOOKUP(F10,'Chart of Accounts'!$C:$E,3,0) -> Income Statement
A11: Service Revenue | C11: 7000 | D11: -7000 | F11: =VLOOKUP($A11,'Chart of Accounts'!F:G,2,0) -> Current Assets | G11: =VLOOKUP(F11,'Chart of Accounts'!$C:$E,3,0) -> #N/A
A12: Utility Expense | B12: 500 | D12: 500 | F12: =VLOOKUP($A12,'Chart of Accounts'!F:G,2,0) -> Expenses | G12: =VLOOKUP(F12,'Chart of Accounts'!$C:$E,3,0) -> Income Statement
A13: Depreciation Expense | B13: 100 | D13: 100 | F13: =VLOOKUP($A13,'Chart of Accounts'!F:G,2,0) -> Expenses | G13: =VLOOKUP(F13,'Chart of Accounts'!$C:$E,3,0) -> Income Statement
A14: Accumlated Expenses | C14: 100 | D14: -100 | F14: =VLOOKUP($A14,'Chart of Accounts'!F:G,2,0) -> Contra Assets | G14: =VLOOKUP(F14,'Chart of Accounts'!$C:$E,3,0) -> #N/A
A15: Payroll | B15: 4500 | D15: 4500 | F15: =VLOOKUP($A15,'Chart of Accounts'!F:G,2,0) -> Expenses | G15: =VLOOKUP(F15,'Chart of Accounts'!$C:$E,3,0) -> Income Statement
A16: Payroll Payable | C16: 1500 | D16: -1500 | F16: =VLOOKUP($A16,'Chart of Accounts'!F:G,2,0) -> Current Liabilities | G16: =VLOOKUP(F16,'Chart of Accounts'!$C:$E,3,0) -> #N/A
A17: Taxes | B17: 58 | D17: 58
A18: Govt | C18: 58 | D18: -58
A19: Grand Total | B19: 30958 | C19: 30958 | D19: 0

Sheet Income Statement
B2: Swift Tech Solutions
B3: Income Statement
B4: For end of January 31st
B5: Revenue
B6: Service Revenue | G6: =_xlfn.XLOOKUP(B6,'Trial Balance'!$A$4:$A$18,'Trial Balance'!$D$4:$D$18,"N/A",0,1)*-1 -> 7000
B7: Gross Profit | H7: =G6 -> 7000
B9: Operating Expenses
B11: Rent Expense | G11: =_xlfn.XLOOKUP(B11,'Trial Balance'!$A$4:$A$18,'Trial Balance'!$D$4:$D$18,"N/A",0,1)*-1 -> -1200
B12: Depreciation Expense | G12: =_xlfn.XLOOKUP(B12,'Trial Balance'!$A$4:$A$18,'Trial Balance'!$D$4:$D$18,"N/A",0,1)*-1 -> -100
B13: Utility Expense | G13: =_xlfn.XLOOKUP(B13,'Trial Balance'!$A$4:$A$18,'Trial Balance'!$D$4:$D$18,"N/A",0,1)*-1 -> -500
B14: Payroll | G14: =_xlfn.XLOOKUP(B14,'Trial Balance'!$A$4:$A$18,'Trial Balance'!$D$4:$D$18,"N/A",0,1)*-1 -> -4500
B15: Total Operating Expenses | H15: =SUM(G11:G14) -> -6300
B16: Operating Profit | H16: =H7+H15 -> 700
B17: Taxes (8.25%) | H17: =H16*-8.25% -> -57.75
B18: Net Income | H18: =SUM(H16:H17) -> 642.25

Sheet Owner's Equity
A1: Swift Tech Solutions
A2: Statement of Owner's Equity
A3: End of January 31st, 2025
A4: Owner's Equity at January 1, 2025
A5: Add:
A6: Owner's Capital Contribution | C6: 10000
A7: Net Income | C7: =_xlfn.XLOOKUP(A7,'Income Statement'!B18,'Income Statement'!H18,"N/A",0,1) -> 642.25
A8: Subtotal | C8: =SUM(C6:C7) -> 10642.25
A9: Deduct:
A10: Owner's Draws | C10: 0
A11: Owner's Equity at January 31, 2025 | C11: =C8-C10 -> 10642.25

Sheet Balance Sheet
A1: Balance Sheet
A2: Year of 2025
A3: Assets | B3: January
A4: Current Assets
A5: Cash | B5: {=_xlfn.XLOOKUP($A5,'Trial Balance'!$A:A,'Trial Balance'!D:D,"N/A",0,1)} -> 4700
A6: Accounts Recieveable | B6: {=_xlfn.XLOOKUP($A6,'Trial Balance'!$A:A,'Trial Balance'!D:D,"N/A",0,1)} -> 5000
A7: Office Supplies | B7: {=_xlfn.XLOOKUP($A7,'Trial Balance'!$A:A,'Trial Balance'!D:D,"N/A",0,1)} -> 600
A8: Total Current Assets | B8: =SUM(B5:B7) -> 10300
A9: Non-Current Assets
A10: Accumlated Expenses | B10: {=_xlfn.XLOOKUP($A10,'Trial Balance'!$A:A,'Trial Balance'!D:D,"N/A",0,1)} -> -100
B11: =IFERROR(VLOOKUP($A11,'Trial Balance'!$A$4:$D$18,4,0), 0) -> 0
A12: Total Non-Current Assets | B12: =SUM(B10) -> -100
A13: Other Assets
A14: Office Furniture | B14: {=_xlfn.XLOOKUP($A14,'Trial Balance'!$A:A,'Trial Balance'!D:D,"N/A",0,1)} -> 2500
B15: {=_xlfn.XLOOKUP($A15,'Trial Balance'!$A:A,'Trial Balance'!D:D,"N/A",0,1)} -> 0
A16: Total Other Assets | B16: =SUM(B14) -> 2500
A17: Total Assets | B17: =SUM(B8+B12+B16) -> 12700
A18: Liabilities and Owner's Equity | B18: January
A19: Current Liabilties
A20: Payroll Payable | B20: {=_xlfn.XLOOKUP($A20,'Trial Balance'!$A:A,'Trial Balance'!D:D,"N/A",0,1)*-1} -> 1500
A21: Accounts Payable | B21: {=_xlfn.XLOOKUP($A21,'Trial Balance'!$A:A,'Trial Balance'!D:D,"N/A",0,1)*-1} -> 500
A22: Govt | B22: {=_xlfn.XLOOKUP($A22,'Trial Balance'!$A:A,'Trial Balance'!D:D,"N/A",0,1)*-1} -> 58
A23: Total Current Liabilities | B23: =SUM(B20:B22) -> 2058
A24: Non - Current Liabilties
B25: =IFERROR(VLOOKUP($A25,'Trial Balance'!$A$4:$D$18,4,0)*-1, 0) -> 0
A26: Total Non-Current Liabilities | B26: =SUM(B25:B25) -> 0
A27: Owner's Equity
A28: Owner's Equity | B28: {=_xlfn.XLOOKUP($A28,'Trial Balance'!$A:A,'Trial Balance'!D:D,"N/A",0,1)} -> -10000
A29: Net Income | B29: ='Income Statement'!H18 -> 642.25
A30: Total Owner's Equity | B30: =SUM(B28:B29) -> -9357.75
A31: Total Liabilities and Owner's Equity | B31: =SUM(B23+B26+B30) -> -7299.75
A32: Financial Ratios | B32: January
A33: Debt Ratio | B33: =(B23+B26)/B17 -> 0.16204724
A34: Current Ratio | B34: =($B$8/$B$23) -> 5.0048591
A35: Working Capital | B35: =($B$8-$B$23) -> 8242
A36: Assets - Equity Ratio | B36: =(B17/B30) -> -1.3571638
A37: Debt - Equity Ratio | B37: =(B23+B26)/B30 -> -0.21992466
